redistools/__init__.py
redis_tools-0.0.2.dist-info/LICENSE.txt
redis_tools-0.0.2.dist-info/METADATA
redis_tools-0.0.2.dist-info/WHEEL
redis_tools-0.0.2.dist-info/top_level.txt
redis_tools-0.0.2.dist-info/RECORD
