Metadata-Version: 2.1
Name: redis-tools
Version: 0.0.2
Summary: Library for inter-service event-based communication
Home-page: https://github.com/radiocut/redis-tools/
Author: Guillermo Narvaja
Author-email: guillermo.narvaja@radiocut.fm
License: UNKNOWN
Project-URL: Bug Reports, https://github.com/radiocutfm/redis-tools/issues
Project-URL: Funding, https://donate.pypi.org
Project-URL: Say Thanks!, https://saythanks.io/to/guillermo.narvaja%40radiocut.fm
Project-URL: Source, https://github.com/radiocutfm/redis-tools/
Keywords: redis rate-limit
Platform: UNKNOWN
Classifier: Development Status :: 3 - Alpha
Classifier: Intended Audience :: Developers
Classifier: License :: OSI Approved :: MIT License
Classifier: Programming Language :: Python :: 3
Classifier: Programming Language :: Python :: 3.6
Classifier: Programming Language :: Python :: 3.7
Classifier: Programming Language :: Python :: 3.8
Requires-Python: >=3.6, !=3.0.*, !=3.1.*, !=3.2.*, !=3.3.*, !=3.4.*, <4
Provides-Extra: dev
Provides-Extra: test
